fastmcp_calculator/__init__.py
fastmcp_calculator/__main__.py
fastmcp_calculator/calculator.py
fastmcp_calculator-0.1.1.dist-info/METADATA
fastmcp_calculator-0.1.1.dist-info/WHEEL
fastmcp_calculator-0.1.1.dist-info/entry_points.txt
fastmcp_calculator-0.1.1.dist-info/top_level.txt
fastmcp_calculator-0.1.1.dist-info/RECORD
