Metadata-Version: 2.4
Name: fastmcp-calculator
Version: 0.1.1
Summary: This is a calculator that includes addition, subtraction, multiplication, and division
Home-page: https://github.com/yourusername/mcp-test1
Author: MCP Developer
Author-email: MCP Developer <example@example.com>
Project-URL: Homepage, https://github.com/yourusername/mcp-test1
Project-URL: Bug Tracker, https://github.com/yourusername/mcp-test1/issues
Classifier: Programming Language :: Python :: 3
Classifier: License :: OSI Approved :: MIT License
Classifier: Operating System :: OS Independent
Requires-Python: >=3.13
Requires-Dist: mcp[cli]>=1.13.0
